{
  "showGettingStartedBanner": false,
  "hasMigratedDailyNoteSettings": false,
  "hasMigratedWeeklyNoteSettings": false,
  "daily": {
    "format": "",
    "template": "",
    "folder": "Daily Notes",
    "enabled": true
  },
  "weekly": {
    "format": "gg-[W]w",
    "template": "",
    "folder": "Weekly Notes",
    "enabled": true
  },
  "monthly": {
    "format": "",
    "template": "",
    "folder": ""
  },
  "quarterly": {
    "format": "",
    "template": "",
    "folder": ""
  },
  "yearly": {
    "format": "",
    "template": "",
    "folder": ""
  }
}